deepgllm/__init__.py
deepgllm-0.0.0.dist-info/METADATA
deepgllm-0.0.0.dist-info/WHEEL
deepgllm-0.0.0.dist-info/top_level.txt
deepgllm-0.0.0.dist-info/RECORD
