Metadata-Version: 2.1
Name: deepgllm
Version: 0.0.0
Summary: deepgllm
Home-page: https://www.aliyun.com
